cmppy/__init__.py
cmppy/connection/__init__.py
cmppy/delivery/__init__.py
cmppy/request/ConnectReq.py
cmppy/request/SubmitReq.py
cmppy/request/TerminateReq.py
cmppy/request/__init__.py
cmppy/response/ConnectRes.py
cmppy/response/SubmitRes.py
cmppy/response/TerminateRes.py
cmppy/response/__init__.py
cmppy-0.3.dist-info/DESCRIPTION.rst
cmppy-0.3.dist-info/METADATA
cmppy-0.3.dist-info/RECORD
cmppy-0.3.dist-info/WHEEL
cmppy-0.3.dist-info/metadata.json
cmppy-0.3.dist-info/top_level.txt
