Metadata-Version: 2.0
Name: cmppy
Version: 0.3
Summary: a Python CMPP client impelemention
Home-page: http://xiangyang.li/project/python_cmppy
Author: Xiangyang Li
Author-email: wo@xiangyang.li
License: Apache License
Keywords: CMPP,CMPP client
Platform: any
